{
    "music": [
        {
            "date": "Nov 22",
            "programs": [
                {
                    "title": "LOCATION ARENA",
                    "list": [
                        {
                            "name": "Sami Yusuf",
                            "time": "00:00 PM",
                            "image": "/2024/artist_images/Performance posters/22 November/Sami-Yusuf.jpg"
                        },
                        {
                            "name": "Senny Camara",
                            "time": "00:00 PM",
                            "image": "/2024/artist_images/Performance posters/22 November/Senny-Camara.jpg"
                        },
                        {
                            "name": "Ziyad Sahhab and Julien Breton",
                            "time": "00:00 PM",
                            "image": "/2024/artist_images/Performance posters/22 November/Ziyad Sahhab Julien Breton.jpg"
                        },
                        {
                            "name": "Heritage Band Al Nadba",
                            "time": "00:00 PM",
                            "image": "/2024/artist_images/Performance posters/22 November/Heritage Band Al Nadba V2.jpg"
                        },
                        {
                            "name": "Anas Alhalabi",
                            "time": "00:00 PM",
                            "image": "/2024/artist_images/Performance posters/22 November/Anas-Alhalabi (1).jpg"
                        }
                    ]
                }
            ]
        },
        {
            "date": "Nov 23",
            "programs": [
                {
                    "title": "LOCATION ARENA",
                    "list": [
                        {
                            "name": "Kamal & Journeys of light",
                            "time": "00:00 PM",
                            "image": "/2024/artist_images/Performance posters/23 November/Journeys of Light.jpg"
                        },
                        {
                            "name": "Abi Sampa & Rushil Ranjan",
                            "time": "00:00 PM",
                            "image": "/2024/artist_images/Performance posters/23 November/Abi Sampa and Rushil Ranjan.jpg"
                        },
                        {
                            "name": "In the Footsteps of Rumi",
                            "time": "00:00 PM",
                            "image": "/2024/artist_images/Performance posters/23 November/In the Footsteps of Rumi_V2.jpg"
                        },
                        {
                            "name": "Senny Camara Mary Malifarges",
                            "time": "00:00 PM",
                            "image": "/2024/artist_images/Performance posters/23 November/Senny-Camara-Mary-Malifarges (1).jpg"
                        },
                        {
                            "name": "Hassan Hakmoun",
                            "time": "00:00 PM",
                            "image": "/2024/artist_images/Performance posters/23 November/Hassan-Hakmoun-23-V2.jpg"
                        },
                        {
                            "name": "Baraka Blue",
                            "time": "00:00 PM",
                            "image": "/2024/artist_images/Performance posters/23 November/Baraka-Blue_V2.jpg"
                        },
                        {
                            "name": "Farima Berenji",
                            "time": "00:00 PM",
                            "image": "/2024/artist_images/Performance posters/23 November/Farima Berenji.jpg"
                        },
                        {
                            "name": "Heritage Band Al Aahaal",
                            "time": "00:00 PM",
                            "image": "/2024/artist_images/Performance posters/23 November/Heritage Band Al Aahaal V1.jpg"
                        },
                        {
                            "name": "Heritage Band Noban",
                            "time": "00:00 PM",
                            "image": "/2024/artist_images/Performance posters/23 November/Heritage Band Noban V1 copy.jpg"
                        },
                        {
                            "name": "Shadi's Band",
                            "time": "00:00 PM",
                            "image": "/2024/artist_images/Performance posters/23 November/Shadi's-Band_V2.jpg"
                        },
                        {
                            "name": "Sandu",
                            "time": "00:00 PM",
                            "image": "/2024/artist_images/Performance posters/23 November/Sandu.jpg"
                        },
                        {
                            "name": "Anas Alhalabi",
                            "time": "00:00 PM",
                            "image": "/2024/artist_images/Performance posters/23 November/Anas-Alhalabi-23 (1).jpg"
                        }
                    ]
                }
            ]
        },
        {
            "date": "Nov 24",
            "programs": [
                {
                    "title": "LOCATION ARENA",
                    "list": [
                        {
                            "name": "Dhafer Youssef",
                            "time": "00:00 PM",
                            "image": "/2024/artist_images/Performance posters/24 November/Dhafer-Youssef (1).jpg"
                        },
                        {
                            "name": "Ensemble Noureddine",
                            "time": "00:00 PM",
                            "image": "/2024/artist_images/Performance posters/24 November/Ensemble-Noureddine-.jpg"
                        },
                        {
                            "name": "Baraka Blue",
                            "time": "00:00 PM",
                            "image": "/2024/artist_images/Performance posters/24 November/Baraka Blue_V2.jpg"
                        },
                        {
                            "name": "Nujoom Al Ghanem",
                            "time": "00:00 PM",
                            "image": "/2024/artist_images/Performance posters/24 November/Nujoom-Al-Ghanem.jpg"
                        },
                        {
                            "name": "Hassan Hakmoun",
                            "time": "00:00 PM",
                            "image": "/2024/artist_images/Performance posters/24 November/Hassan-Hakmoun-V2-24.jpg"
                        },
                        {
                            "name": "Heritage Band Al Malad",
                            "time": "00:00 PM",
                            "image": "/2024/artist_images/Performance posters/24 November/Heritage Band Al Malad V1.jpg"
                        },
                        {
                            "name": "Heritage Band Al Waliyah",
                            "time": "00:00 PM",
                            "image": "/2024/artist_images/Performance posters/24 November/Heritage Band Al Waliyah V2.jpg"
                        },
                        {
                            "name": "Heritage Band Al Liwah",
                            "time": "00:00 PM",
                            "image": "/2024/artist_images/Performance posters/24 November/Heritage-Band-Al-Liwah-V1.jpg"
                        },
                        {
                            "name": "Fadi Rifaai and Sandu & Zahi Saba",
                            "time": "00:00 PM",
                            "image": "/2024/artist_images/Performance posters/24 November/Fadi Rifaai and Sandu & Zahi Saba_V3-1.jpg"
                        },
                        {
                            "name": "Sandu",
                            "time": "00:00 PM",
                            "image": "/2024/artist_images/Performance posters/24 November/Sandu - 2.jpg"
                        },
                        {
                            "name": "Shadi's Band",
                            "time": "00:00 PM",
                            "image": "/2024/artist_images/Performance posters/24 November/Shadi's Band_V2.jpg"
                        }
                    ]
                }
            ]
        }
    ],
    "workshops": [
        {
            "date": "Nov 22",
            "programs": [
                {
                    "title": "LOCATION ARENA",
                    "list": []
                }
            ]
        },
        {
            "date": "Nov 23",
            "programs": [
                {
                    "title": "LOCATION ARENA",
                    "list": [
                        {
                            "name": "Breathwork",
                            "time": "00:00 PM",
                            "image": "/2024/artist_images/Workshop Posters-V2/November 23/Breathwork_V4.jpg"
                        },
                        {
                            "name": "Anas Handpan Orchestra",
                            "time": "00:00 PM",
                            "image": "/2024/artist_images/Workshop Posters-V2/November 23/Anas-Handpan-Orchestra_V2.jpg"
                        },
                        {
                            "name": "Illumination and Geometry",
                            "time": "00:00 PM",
                            "image": "/2024/artist_images/Workshop Posters-V2/November 23/Illumination-and-Geometry_V3_Nov23.jpg"
                        },
                        {
                            "name": "Sema Whirling",
                            "time": "00:00 PM",
                            "image": "/2024/artist_images/Workshop Posters-V2/November 23/Sema Whirling_V2.jpg"
                        },
                        {
                            "name": "Calligraphy Lighting",
                            "time": "00:00 PM",
                            "image": "/2024/artist_images/Workshop Posters-V2/November 23/Calligraphy Lighting_V2_Nov23.jpg"
                        }
                    ]
                }
            ]
        },
        {
            "date": "Nov 24",
            "programs": [
                {
                    "title": "LOCATION ARENA",
                    "list": [
                        {
                            "name": "Sound Immersion",
                            "time": "00:00 PM",
                            "image": "/2024/artist_images/Workshop Posters-V2/November 24/Sound Immersion_V3.jpg"
                        },
                        {
                            "name": "Whirling",
                            "time": "00:00 PM",
                            "image": "/2024/artist_images/Workshop Posters-V2/November 24/Whirling_V2.jpg"
                        },
                        {
                            "name": "Illumination and Geometry",
                            "time": "00:00 PM",
                            "image": "/2024/artist_images/Workshop Posters-V2/November 24/Illumination-and-Geometry_V3_Nov24.jpg"
                        },
                        {
                            "name": "Calligraphy",
                            "time": "00:00 PM",
                            "image": "/2024/artist_images/Workshop Posters-V2/November 24/Calligraphy_V2_Nov24.jpg"
                        },
                        {
                            "name": "Calligraphy Lighting",
                            "time": "00:00 PM",
                            "image": "/2024/artist_images/Workshop Posters-V2/November 24/Calligraphy Lighting_V2_Nov24.jpg"
                        }
                    ]
                }
            ]
        }
    ]
}